django_widgets_improved-1.5.0.dist-info/DESCRIPTION.rst
django_widgets_improved-1.5.0.dist-info/METADATA
django_widgets_improved-1.5.0.dist-info/RECORD
django_widgets_improved-1.5.0.dist-info/WHEEL
django_widgets_improved-1.5.0.dist-info/metadata.json
django_widgets_improved-1.5.0.dist-info/top_level.txt
widget_tweaks/__init__.py
widget_tweaks/models.py
widget_tweaks/tests.py
widget_tweaks/templatetags/__init__.py
widget_tweaks/templatetags/widget_tweaks.py
