Metadata-Version: 1.1
Name: django-widgets-improved
Version: 1.5.0
Summary: Tweak the form field rendering in templates, not in python-level form definitions.
Home-page: https://github.com/simhnna/django-widgets-improved
Author: Simon Hanna
Author-email: simhnna@gmail.com
License: MIT license
Platform: UNKNOWN
Classifier: Development Status :: 5 - Production/Stable
Classifier: Framework :: Django
Classifier: Intended Audience :: Developers
Classifier: License :: OSI Approved :: MIT License
Classifier: Programming Language :: Python
Classifier: Programming Language :: Python :: 2
Classifier: Programming Language :: Python :: 2.7
Classifier: Programming Language :: Python :: 3
Classifier: Programming Language :: Python :: 3.4
Classifier: Programming Language :: Python :: 3.5
Classifier: Programming Language :: Python :: 3.6
Classifier: Topic :: Software Development :: Libraries :: Python Modules
Requires: django (>= 1.8)
